<?xml version="1.0" ?>
<upgradepathes>
	<upgrade from_pdid="820" from_product="SUSE-Linux-Enterprise-Server-SP2-10-None.i686" to_pdid="1500" to_product="SUSE-Linux-Enterprise-Server-SP3-10-None.i686"/>
	<upgrade from_pdid="821" from_product="SUSE-Linux-Enterprise-Server-SP2-10-None.i586" to_pdid="1501" to_product="SUSE-Linux-Enterprise-Server-SP3-10-None.i586"/>
	<upgrade from_pdid="822" from_product="SUSE-Linux-Enterprise-Server-SP2-10-None.i486" to_pdid="1502" to_product="SUSE-Linux-Enterprise-Server-SP3-10-None.i486"/>
	<upgrade from_pdid="823" from_product="SUSE-Linux-Enterprise-Server-SP2-10-None.i386" to_pdid="1503" to_product="SUSE-Linux-Enterprise-Server-SP3-10-None.i386"/>
	<upgrade from_pdid="824" from_product="SUSE-Linux-Enterprise-Server-SP2-10-None.x86_64" to_pdid="1504" to_product="SUSE-Linux-Enterprise-Server-SP3-10-None.x86_64"/>
	<upgrade from_pdid="825" from_product="SUSE-Linux-Enterprise-Server-SP2-10-None.ppc" to_pdid="1505" to_product="SUSE-Linux-Enterprise-Server-SP3-10-None.ppc"/>
	<upgrade from_pdid="826" from_product="SUSE-Linux-Enterprise-Server-SP2-10-None.ppc64" to_pdid="1506" to_product="SUSE-Linux-Enterprise-Server-SP3-10-None.ppc64"/>
	<upgrade from_pdid="827" from_product="SUSE-Linux-Enterprise-Server-SP2-10-None.ia64" to_pdid="1507" to_product="SUSE-Linux-Enterprise-Server-SP3-10-None.ia64"/>
	<upgrade from_pdid="828" from_product="SUSE-Linux-Enterprise-Server-SP2-10-None.s390" to_pdid="1508" to_product="SUSE-Linux-Enterprise-Server-SP3-10-None.s390"/>
	<upgrade from_pdid="829" from_product="SUSE-Linux-Enterprise-Server-SP2-10-None.s390x" to_pdid="1509" to_product="SUSE-Linux-Enterprise-Server-SP3-10-None.s390x"/>
	<upgrade from_pdid="880" from_product="SUSE-Linux-Enterprise-SDK-SP2-10-None.None" to_pdid="1541" to_product="SUSE-Linux-Enterprise-SDK-SP3-10-None.None"/>
	<upgrade from_pdid="1460" from_product="sle-smt-11-None.None" to_pdid="3260" to_product="sle-smt-11.2-None.None"/>
	<upgrade from_pdid="1500" from_product="SUSE-Linux-Enterprise-Server-SP3-10-None.i686" to_pdid="2522" to_product="SUSE-Linux-Enterprise-Server-SP4-10-None.i686"/>
	<upgrade from_pdid="1501" from_product="SUSE-Linux-Enterprise-Server-SP3-10-None.i586" to_pdid="2523" to_product="SUSE-Linux-Enterprise-Server-SP4-10-None.i586"/>
	<upgrade from_pdid="1502" from_product="SUSE-Linux-Enterprise-Server-SP3-10-None.i486" to_pdid="2524" to_product="SUSE-Linux-Enterprise-Server-SP4-10-None.i486"/>
	<upgrade from_pdid="1503" from_product="SUSE-Linux-Enterprise-Server-SP3-10-None.i386" to_pdid="2525" to_product="SUSE-Linux-Enterprise-Server-SP4-10-None.i386"/>
	<upgrade from_pdid="1504" from_product="SUSE-Linux-Enterprise-Server-SP3-10-None.x86_64" to_pdid="2526" to_product="SUSE-Linux-Enterprise-Server-SP4-10-None.x86_64"/>
	<upgrade from_pdid="1505" from_product="SUSE-Linux-Enterprise-Server-SP3-10-None.ppc" to_pdid="2527" to_product="SUSE-Linux-Enterprise-Server-SP4-10-None.ppc"/>
	<upgrade from_pdid="1506" from_product="SUSE-Linux-Enterprise-Server-SP3-10-None.ppc64" to_pdid="2528" to_product="SUSE-Linux-Enterprise-Server-SP4-10-None.ppc64"/>
	<upgrade from_pdid="1507" from_product="SUSE-Linux-Enterprise-Server-SP3-10-None.ia64" to_pdid="2529" to_product="SUSE-Linux-Enterprise-Server-SP4-10-None.ia64"/>
	<upgrade from_pdid="1508" from_product="SUSE-Linux-Enterprise-Server-SP3-10-None.s390" to_pdid="2530" to_product="SUSE-Linux-Enterprise-Server-SP4-10-None.s390"/>
	<upgrade from_pdid="1509" from_product="SUSE-Linux-Enterprise-Server-SP3-10-None.s390x" to_pdid="2531" to_product="SUSE-Linux-Enterprise-Server-SP4-10-None.s390x"/>
	<upgrade from_pdid="1541" from_product="SUSE-Linux-Enterprise-SDK-SP3-10-None.None" to_pdid="2534" to_product="SUSE-Linux-Enterprise-SDK-SP4-10-None.None"/>
	<upgrade from_pdid="1820" from_product="SUSE_SLED-11.1-None.i686" to_pdid="3000" to_product="SUSE_SLED-11.2-None.i686"/>
	<upgrade from_pdid="1821" from_product="SUSE_SLED-11.1-None.i586" to_pdid="3001" to_product="SUSE_SLED-11.2-None.i586"/>
	<upgrade from_pdid="1822" from_product="SUSE_SLED-11.1-None.i486" to_pdid="3002" to_product="SUSE_SLED-11.2-None.i486"/>
	<upgrade from_pdid="1823" from_product="SUSE_SLED-11.1-None.i386" to_pdid="3003" to_product="SUSE_SLED-11.2-None.i386"/>
	<upgrade from_pdid="1824" from_product="SUSE_SLED-11.1-None.x86_64" to_pdid="3004" to_product="SUSE_SLED-11.2-None.x86_64"/>
	<upgrade from_pdid="1825" from_product="SUSE_SLES-11.1-None.i686" to_pdid="3005" to_product="SUSE_SLES-11.2-None.i686"/>
	<upgrade from_pdid="1826" from_product="SUSE_SLES-11.1-None.i586" to_pdid="3006" to_product="SUSE_SLES-11.2-None.i586"/>
	<upgrade from_pdid="1827" from_product="SUSE_SLES-11.1-None.i486" to_pdid="3007" to_product="SUSE_SLES-11.2-None.i486"/>
	<upgrade from_pdid="1828" from_product="SUSE_SLES-11.1-None.i386" to_pdid="3008" to_product="SUSE_SLES-11.2-None.i386"/>
	<upgrade from_pdid="1829" from_product="SUSE_SLES-11.1-None.x86_64" to_pdid="3009" to_product="SUSE_SLES-11.2-None.x86_64"/>
	<upgrade from_pdid="1831" from_product="SUSE_SLES-11.1-None.ppc64" to_pdid="3011" to_product="SUSE_SLES-11.2-None.ppc64"/>
	<upgrade from_pdid="1832" from_product="SUSE_SLES-11.1-None.ia64" to_pdid="3012" to_product="SUSE_SLES-11.2-None.ia64"/>
	<upgrade from_pdid="1833" from_product="SUSE_SLES-11.1-None.s390" to_pdid="3013" to_product="SUSE_SLES-11.2-None.s390"/>
	<upgrade from_pdid="1834" from_product="SUSE_SLES-11.1-None.s390x" to_pdid="3014" to_product="SUSE_SLES-11.2-None.s390x"/>
	<upgrade from_pdid="1860" from_product="sle-sdk-11.1-None.None" to_pdid="3040" to_product="sle-sdk-11.2-None.None"/>
	<upgrade from_pdid="1880" from_product="sle-hae-11.1-None.i686" to_pdid="3080" to_product="sle-hae-11.2-None.i686"/>
	<upgrade from_pdid="1881" from_product="sle-hae-11.1-None.i586" to_pdid="3081" to_product="sle-hae-11.2-None.i586"/>
	<upgrade from_pdid="1882" from_product="sle-hae-11.1-None.i486" to_pdid="3082" to_product="sle-hae-11.2-None.i486"/>
	<upgrade from_pdid="1883" from_product="sle-hae-11.1-None.i386" to_pdid="3083" to_product="sle-hae-11.2-None.i386"/>
	<upgrade from_pdid="1884" from_product="sle-hae-11.1-None.x86_64" to_pdid="3084" to_product="sle-hae-11.2-None.x86_64"/>
	<upgrade from_pdid="1886" from_product="sle-hae-11.1-None.ppc64" to_pdid="3086" to_product="sle-hae-11.2-None.ppc64"/>
	<upgrade from_pdid="1887" from_product="sle-hae-11.1-None.ia64" to_pdid="3087" to_product="sle-hae-11.2-None.ia64"/>
	<upgrade from_pdid="1889" from_product="sle-hae-11.1-None.s390x" to_pdid="3089" to_product="sle-hae-11.2-None.s390x"/>
	<upgrade from_pdid="2240" from_product="SUSE-Linux-Enterprise-RT-11.1-None.None" to_pdid="3580" to_product="SUSE-Linux-Enterprise-RT-11.2-None.None"/>
	<upgrade from_pdid="2320" from_product="SUSE_SLES-11.1-VMWARE.None" to_pdid="3060" to_product="SLES-for-VMware-11.2-None.None"/>
	<upgrade from_pdid="2680" from_product="SUSE-Manager-Proxy-1.2-None.None" to_pdid="3640" to_product="SUSE-Manager-Proxy-1.7-None.x86_64"/>
	<upgrade from_pdid="2980" from_product="Open_Enterprise_Server-11-None.None" to_pdid="3480" to_product="Open_Enterprise_Server-11.1-None.None"/>
</upgradepathes>
